brainblocks/__init__.py
brainblocks/__main__.py
brainblocks/bb_backend.cp38-win_amd64.pyd
brainblocks/blocks/__init__.py
brainblocks/blocks/blocks.py
brainblocks/datasets/__init__.py
brainblocks/datasets/classification.py
brainblocks/datasets/time_series.py
brainblocks/metrics/__init__.py
brainblocks/templates/__init__.py
brainblocks/templates/anomaly_detector.py
brainblocks/templates/anomaly_detector_persist.py
brainblocks/templates/classifier.py
brainblocks/tools/__init__.py
brainblocks/tools/bbclassifier.py
brainblocks/tools/hypergrid_transform.py
brainblocks-0.7.1.dist-info/LICENSE
brainblocks-0.7.1.dist-info/METADATA
brainblocks-0.7.1.dist-info/WHEEL
brainblocks-0.7.1.dist-info/top_level.txt
brainblocks-0.7.1.dist-info/RECORD
