Metadata-Version: 2.1
Name: brainblocks
Version: 0.7.1
Summary: BrainBlocks Toolkit
Home-page: https://github.com/the-aerospace-corporation/brainblocks
Author: Jacob Everist, David Di Giorgio
Author-email: jacob.everist@gmail.com, ddigiorg@gmail.com
License: GNU Affero General Public License v3.0 only
Keywords: brainblocks,htm,classification,anomaly,abnormality,time-series,neuroscience,cognitive,distributed,representation
Platform: UNKNOWN
Classifier: Topic :: Scientific/Engineering :: Artificial Intelligence
Classifier: Programming Language :: C
Classifier: Programming Language :: Python :: 3
Classifier: Development Status :: 3 - Alpha
Classifier: Operating System :: MacOS :: MacOS X
Classifier: Operating System :: Microsoft :: Windows
Classifier: Operating System :: POSIX :: Linux
Classifier: License :: OSI Approved :: GNU Affero General Public License v3
Requires-Python: >=3.6
License-File: LICENSE
Requires-Dist: numpy (>=1.18.5)
Requires-Dist: scipy (>=1.5.4)
Requires-Dist: scikit-learn (>=0.22.1)
